{
  "parent": "things:gleaming_powder",
  "display": {
    "icon": {
      "item": "things:item_magnet"
    },
    "title": {
      "translate": "advancement.things.item_magnet.title"
    },
    "description": {
      "translate": "advancement.things.item_magnet.description"
    },
    "frame": "task",
    "show_toast": true,
    "announce_to_chat": true,
    "hidden": false
  },
  "criteria": {
    "item_magnet": {
      "trigger": "minecraft:inventory_changed",
      "conditions": {
        "items": [
          {
            "items": [
              "things:item_magnet"
            ]
          }
        ]
      }
    }
  },
  "requirements": [
    [
      "item_magnet"
    ]
  ]
}