{
    "type": "minecraft:crafting_shaped",
    "pattern": [
        "RNP",
        "ICI",
        "PNR"
    ],
    "key": {
        "R": {
            "item": "minecraft:redstone_block"
        },
        "N": {
            "item": "minecraft:netherite_ingot"
        },
        "I": {
            "item": "minecraft:iron_ingot"
        },
        "C": {
            "item": "things:gleaming_compound"
        },
        "P": {
            "item": "minecraft:piston"
        }
    },
    "result": {
        "item": "things:arm_extender"
    }
}